semv/__init__.py
semv/changelog.py
semv/commands.py
semv/config.py
semv/errors.py
semv/hooks.py
semv/increment.py
semv/interface.py
semv/main.py
semv/parse.py
semv/py.typed
semv/types.py
semv/utils.py
semv/version_control_system.py
semv-2.5.0.dist-info/LICENSE
semv-2.5.0.dist-info/METADATA
semv-2.5.0.dist-info/WHEEL
semv-2.5.0.dist-info/entry_points.txt
semv-2.5.0.dist-info/top_level.txt
semv-2.5.0.dist-info/RECORD
