Metadata-Version: 2.1
Name: semv
Version: 2.5.0
Summary: A read-only semantic version commit parsing and validation tool
Author-email: Ingo Fruend <github@ingofruend.net>
License: BSD-3-Clause
Keywords: Semantic Versioning
License-File: LICENSE
Requires-Dist: tomli
